<annotation>
    <folder>dataset</folder>
    <filename>430722_orig.jpg</filename>
    <path>/content/gdrive/My Drive/Colab Notebooks/ssd_keras/dataset/430722_orig.jpg</path>
    <source>
        <database>Unknown</database>
    </source>
    <size>
        <width>1100</width>
        <height>660</height>
        <depth>3</depth>
    </size>
    <segmented>0</segmented>
    <object>
        <name>civilian aircraft</name>
        <pose>Unspecified</pose>
        <truncated>0</truncated>
        <difficult>1</difficult>
        <bndbox>
            <xmin>165</xmin>
            <ymin>309</ymin>
            <xmax>950</xmax>
            <ymax>584</ymax>
        </bndbox>
    </object>
</annotation>
