<annotation>
    <folder>dataset</folder>
    <filename>images361(10).jpg</filename>
    <path>/content/gdrive/My Drive/Colab Notebooks/ssd_keras/dataset/images361(10).jpg</path>
    <source>
        <database>Unknown</database>
    </source>
    <size>
        <width>322</width>
        <height>156</height>
        <depth>3</depth>
    </size>
    <segmented>0</segmented>
    <object>
        <name>civilian aircraft</name>
        <pose>Unspecified</pose>
        <truncated>0</truncated>
        <difficult>1</difficult>
        <bndbox>
            <xmin>152</xmin>
            <ymin>10</ymin>
            <xmax>290</xmax>
            <ymax>76</ymax>
        </bndbox>
    </object>
</annotation>
