<annotation>
    <folder>dataset</folder>
    <filename>images288(9).jpg</filename>
    <path>/content/gdrive/My Drive/Colab Notebooks/ssd_keras/dataset/images288(9).jpg</path>
    <source>
        <database>Unknown</database>
    </source>
    <size>
        <width>332</width>
        <height>152</height>
        <depth>3</depth>
    </size>
    <segmented>0</segmented>
    <object>
        <name>civilian car</name>
        <pose>Unspecified</pose>
        <truncated>0</truncated>
        <difficult>1</difficult>
        <bndbox>
            <xmin>92</xmin>
            <ymin>11</ymin>
            <xmax>241</xmax>
            <ymax>134</ymax>
        </bndbox>
    </object>
</annotation>
