<annotation>
    <folder>dataset</folder>
    <filename>m1-tank-classic.jpg</filename>
    <path>/content/gdrive/My Drive/Colab Notebooks/ssd_keras/dataset/m1-tank-classic.jpg</path>
    <source>
        <database>Unknown</database>
    </source>
    <size>
        <width>400</width>
        <height>308</height>
        <depth>3</depth>
    </size>
    <segmented>0</segmented>
    <object>
        <name>military tank</name>
        <pose>Unspecified</pose>
        <truncated>0</truncated>
        <difficult>1</difficult>
        <bndbox>
            <xmin>16</xmin>
            <ymin>69</ymin>
            <xmax>349</xmax>
            <ymax>267</ymax>
        </bndbox>
    </object>
</annotation>
