<annotation>
    <folder>dataset</folder>
    <filename>maxresdefault1(7).jpg</filename>
    <path>/content/gdrive/My Drive/Colab Notebooks/ssd_keras/dataset/maxresdefault1(7).jpg</path>
    <source>
        <database>Unknown</database>
    </source>
    <size>
        <width>1280</width>
        <height>720</height>
        <depth>3</depth>
    </size>
    <segmented>0</segmented>
    <object>
        <name>civilian car</name>
        <pose>Unspecified</pose>
        <truncated>0</truncated>
        <difficult>1</difficult>
        <bndbox>
            <xmin>691</xmin>
            <ymin>290</ymin>
            <xmax>1235</xmax>
            <ymax>699</ymax>
        </bndbox>
    </object>
</annotation>
