<annotation>
    <folder>dataset</folder>
    <filename>mbt-arjun-tank-models-500x500.jpg</filename>
    <path>/content/gdrive/My Drive/Colab Notebooks/ssd_keras/dataset/mbt-arjun-tank-models-500x500.jpg</path>
    <source>
        <database>Unknown</database>
    </source>
    <size>
        <width>425</width>
        <height>242</height>
        <depth>3</depth>
    </size>
    <segmented>0</segmented>
    <object>
        <name>military tank</name>
        <pose>Unspecified</pose>
        <truncated>0</truncated>
        <difficult>1</difficult>
        <bndbox>
            <xmin>19</xmin>
            <ymin>17</ymin>
            <xmax>400</xmax>
            <ymax>233</ymax>
        </bndbox>
    </object>
</annotation>
